setup.cfg
setup.py
boxup_gmailunread/__init__.py
boxup_gmailunread/boxup_gmailunread.py
boxup_gmailunread.egg-info/PKG-INFO
boxup_gmailunread.egg-info/SOURCES.txt
boxup_gmailunread.egg-info/dependency_links.txt
boxup_gmailunread.egg-info/requires.txt
boxup_gmailunread.egg-info/top_level.txt