Metadata-Version: 1.1
Name: boxup-gmailunread
Version: 0.0.2
Summary: datasource of unread emails for boxup input.
Home-page: https://github.com/xamgreen/boxup_gmailunread
Author: Maximilian, Noppel
Author-email: noppelmax@googlemail.com
License: GPLv2, see LICENSE.txt
Download-URL: https://github.com/xamgreen/boxup_weatherradar/tarball/0.0.2
Keywords: gmail,raspberrypi,gpio
Platform: UNKNOWN
